README.md
setup.py
dtrspnsy/__init__.py
dtrspnsy/__main__.py
dtrspnsy/config_wikiEN.py
dtrspnsy/config_wikiRU.py
dtrspnsy/config_wikiZH.py
dtrspnsy/dtrspnsy.py
dtrspnsy/parse_wikiEN.py
dtrspnsy/parse_wikiRU.py
dtrspnsy/parse_wikiZH.py
dtrspnsy/strutils_wiki.py
dtrspnsy.egg-info/PKG-INFO
dtrspnsy.egg-info/SOURCES.txt
dtrspnsy.egg-info/dependency_links.txt
dtrspnsy.egg-info/entry_points.txt
dtrspnsy.egg-info/requires.txt
dtrspnsy.egg-info/top_level.txt
dtrspnsy/en_replics/Abaddon.json
dtrspnsy/en_replics/Acolyte of the Lost Arts.json
dtrspnsy/en_replics/Alchemist.json
dtrspnsy/en_replics/Ancient Apparition.json
dtrspnsy/en_replics/Announcer responses.json
dtrspnsy/en_replics/Anti-Mage.json
dtrspnsy/en_replics/Arc Warden.json
dtrspnsy/en_replics/Axe Announcer Pack.json
dtrspnsy/en_replics/Axe Unleashed.json
dtrspnsy/en_replics/Axe.json
dtrspnsy/en_replics/Bane.json
dtrspnsy/en_replics/Bastion Announcer Pack.json
dtrspnsy/en_replics/Batrider.json
dtrspnsy/en_replics/Beastmaster.json
dtrspnsy/en_replics/Bloodseeker.json
dtrspnsy/en_replics/Bounty Hunter.json
dtrspnsy/en_replics/Brewmaster.json
dtrspnsy/en_replics/Bristleback Announcer Pack.json
dtrspnsy/en_replics/Bristleback.json
dtrspnsy/en_replics/Broodmother.json
dtrspnsy/en_replics/Call of the Bladeform Legacy.json
dtrspnsy/en_replics/Centaur Warrunner.json
dtrspnsy/en_replics/Chaos Knight.json
dtrspnsy/en_replics/Chen.json
dtrspnsy/en_replics/Clinkz.json
dtrspnsy/en_replics/Clockwerk Announcer Pack.json
dtrspnsy/en_replics/Clockwerk.json
dtrspnsy/en_replics/Crystal Maiden Announcer Pack.json
dtrspnsy/en_replics/Crystal Maiden.json
dtrspnsy/en_replics/Dark Seer.json
dtrspnsy/en_replics/Dark Willow Announcer Pack.json
dtrspnsy/en_replics/Dark Willow.json
dtrspnsy/en_replics/Darkest Dungeon Announcer Pack (ft. Wayne June).json
dtrspnsy/en_replics/Dazzle.json
dtrspnsy/en_replics/Death Prophet.json
dtrspnsy/en_replics/Defense Grid Announcer Pack.json
dtrspnsy/en_replics/Deus Ex Announcer Pack.json
dtrspnsy/en_replics/Disruptor.json
dtrspnsy/en_replics/Doom.json
dtrspnsy/en_replics/Dragon Knight.json
dtrspnsy/en_replics/Drow Ranger.json
dtrspnsy/en_replics/Earth Spirit.json
dtrspnsy/en_replics/Earthshaker.json
