Metadata-Version: 2.1
Name: dtrspnsy
Version: 0.0.2
Summary: search dota 2 responses english/russian/chinese
Home-page: https://github.com/dota2tools/dtrspnsy
Author: upgradehq
Author-email: noreply@example.com
License: UNKNOWN
Platform: UNKNOWN
Classifier: Programming Language :: Python :: 3
Classifier: License :: OSI Approved :: MIT License
Classifier: Operating System :: OS Independent
Requires-Python: >=3.6
